data_memory/__init__.py
data_memory/main.py
dataframe_memory-2023.3.1.dist-info/LICENSE
dataframe_memory-2023.3.1.dist-info/METADATA
dataframe_memory-2023.3.1.dist-info/WHEEL
dataframe_memory-2023.3.1.dist-info/top_level.txt
dataframe_memory-2023.3.1.dist-info/RECORD
