Metadata-Version: 2.1
Name: dataframe-memory
Version: 2023.3.1
Summary: Reduce pandas' dataframe memory usage
Author-email: Eurobios <contact_ost@eurobios.com>
License: Apache License
Project-URL: repository, https://github.com/eurobios-mews-labs/dataframe-memory.git
Keywords: data,dataframe
Classifier: Programming Language :: Python
Classifier: Programming Language :: Python :: 3
Requires-Python: >=3.6
License-File: LICENSE
Requires-Dist: numpy
Requires-Dist: pandas
